asn1crypto/__init__.py
asn1crypto/_errors.py
asn1crypto/_inet.py
asn1crypto/_int.py
asn1crypto/_iri.py
asn1crypto/_ordereddict.py
asn1crypto/_teletex_codec.py
asn1crypto/_types.py
asn1crypto/algos.py
asn1crypto/cms.py
asn1crypto/core.py
asn1crypto/crl.py
asn1crypto/csr.py
asn1crypto/keys.py
asn1crypto/ocsp.py
asn1crypto/parser.py
asn1crypto/pdf.py
asn1crypto/pem.py
asn1crypto/pkcs12.py
asn1crypto/tsp.py
asn1crypto/util.py
asn1crypto/version.py
asn1crypto/x509.py
asn1crypto-1.5.0.dist-info/LICENSE
asn1crypto-1.5.0.dist-info/METADATA
asn1crypto-1.5.0.dist-info/WHEEL
asn1crypto-1.5.0.dist-info/top_level.txt
asn1crypto-1.5.0.dist-info/RECORD
