Metadata-Version: 2.1
Name: asn1crypto
Version: 1.5.0
Summary: Fast ASN.1 parser and serializer with definitions for private keys, public keys, certificates, CRL, OCSP, CMS, PKCS#3, PKCS#7, PKCS#8, PKCS#12, PKCS#5, X.509 and TSP
Home-page: https://github.com/wbond/asn1crypto
Author: wbond
Author-email: will@wbond.net
License: MIT
Keywords: asn1 crypto pki x509 certificate rsa dsa ec dh
Platform: UNKNOWN
Classifier: Development Status :: 5 - Production/Stable
Classifier: Intended Audience :: Developers
Classifier: License :: OSI Approved :: MIT License
Classifier: Programming Language :: Python
Classifier: Programming Language :: Python :: 2
Classifier: Programming Language :: Python :: 2.6
Classifier: Programming Language :: Python :: 2.7
Classifier: Programming Language :: Python :: 3
Classifier: Programming Language :: Python :: 3.2
Classifier: Programming Language :: Python :: 3.3
Classifier: Programming Language :: Python :: 3.4
Classifier: Programming Language :: Python :: 3.5
Classifier: Programming Language :: Python :: 3.6
Classifier: Programming Language :: Python :: 3.7
Classifier: Programming Language :: Python :: 3.8
Classifier: Programming Language :: Python :: 3.9
Classifier: Programming Language :: Python :: 3.10
Classifier: Programming Language :: Python :: Implementation :: CPython
Classifier: Programming Language :: Python :: Implementation :: PyPy
Classifier: Topic :: Security :: Cryptography
License-File: LICENSE
